Metadata-Version: 2.4
Name: homekitng
Version: 0.20.1
Summary: Python code to interface HomeKit Accessories and Controllers
Home-page: https://github.com/pierrekin/homekit_python
Download-URL: https://example.com/jlusiardi/homekit_python/archive/0.18.0.tar.gz
Author: Pierre Hugo
Author-email: pierrekin@househugo.com
License: Apache License 2.0
Keywords: HomeKit
Classifier: License :: OSI Approved :: Apache Software License
Classifier: Topic :: Home Automation
Classifier: Intended Audience :: Developers
Classifier: Intended Audience :: End Users/Desktop
License-File: LICENSE
License-File: LICENSE.md
Requires-Dist: hkdf
Requires-Dist: PyNaCl
Requires-Dist: cryptography
Requires-Dist: tlv8
Provides-Extra: ip
Requires-Dist: zeroconf; extra == "ip"
Dynamic: author
Dynamic: author-email
Dynamic: classifier
Dynamic: description
Dynamic: description-content-type
Dynamic: download-url
Dynamic: home-page
Dynamic: keywords
Dynamic: license
Dynamic: license-file
Dynamic: provides-extra
Dynamic: requires-dist
Dynamic: summary
